README.md
setup.py
openspeechcorpus.egg-info/PKG-INFO
openspeechcorpus.egg-info/SOURCES.txt
openspeechcorpus.egg-info/dependency_links.txt
openspeechcorpus.egg-info/not-zip-safe
openspeechcorpus.egg-info/requires.txt
openspeechcorpus.egg-info/top_level.txt
openspeechcorpus_cli/__init__.py
openspeechcorpus_cli/ops.py
openspeechcorpus_cli/ops_client.py
openspeechcorpus_cli/recursive_convert.py
openspeechcorpus_cli/bin/clean_previous_configuration
openspeechcorpus_cli/bin/configure_htk
openspeechcorpus_cli/bin/configure_sphinx
openspeechcorpus_cli/bin/generate_htk_flat_start
openspeechcorpus_cli/bin/generate_sphinx_language_model
openspeechcorpus_cli/bin/ops
openspeechcorpus_cli/bin/recursive_convert
openspeechcorpus_cli/cmu_sphinx/__init__.py
openspeechcorpus_cli/cmu_sphinx/clean_previous_configuration.py
openspeechcorpus_cli/cmu_sphinx/configure_sphinx_etc_files.py
openspeechcorpus_cli/cmu_sphinx/generate_dict.py
openspeechcorpus_cli/cmu_sphinx/generate_fileids.py
openspeechcorpus_cli/cmu_sphinx/generate_filler.py
openspeechcorpus_cli/cmu_sphinx/generate_lm_transcription.py
openspeechcorpus_cli/cmu_sphinx/generate_phone_set_from_dict.py
openspeechcorpus_cli/cmu_sphinx/generate_transcriptions.py
openspeechcorpus_cli/htk/__init__.py
openspeechcorpus_cli/htk/configure_isolated_words_model.py
openspeechcorpus_cli/htk/generate_config_file.py
openspeechcorpus_cli/htk/generate_dict.py
openspeechcorpus_cli/htk/generate_features_map_file.py
openspeechcorpus_cli/htk/generate_flat_start.py
openspeechcorpus_cli/htk/generate_isolated_words_grammar.py
openspeechcorpus_cli/htk/generate_list_phonemes.py
openspeechcorpus_cli/htk/generate_list_words.py
openspeechcorpus_cli/htk/generate_phone_level_master_labeled_file.py
openspeechcorpus_cli/htk/generate_prototype.py
openspeechcorpus_cli/htk/generate_word_level_master_labeled_file.py
openspeechcorpus_cli/utils/__init__.py
openspeechcorpus_cli/utils/common_filters.py
openspeechcorpus_cli/utils/download.py
openspeechcorpus_cli/utils/files.py
openspeechcorpus_cli/utils/transcription.py