Metadata-Version: 2.1
Name: openspeechcorpus
Version: 0.2.1
Summary: The CLI for perform actions over the Open Speech Corpus
Home-page: https://github.com/open-speech-org/openspeechcorpus-cli
Author: contraslash S.A.S.
Author-email: ma0@contraslash.com
License: MIT
Project-URL: Bug Reports, https://github.com/open-speech-org/openspeechcorpus-cli/issues
Project-URL: Source, https://github.com/open-speech-org/openspeechcorpus-cli
Project-URL: Contraslash, https://contraslash.com/
Platform: UNKNOWN
Classifier: Development Status :: 3 - Alpha
Classifier: Intended Audience :: Developers
Classifier: License :: OSI Approved :: MIT License
Classifier: Programming Language :: Python :: 3
